zeptum/__init__.py
zeptum/core.py
zeptum-1.0.1.dist-info/METADATA
zeptum-1.0.1.dist-info/WHEEL
zeptum-1.0.1.dist-info/top_level.txt
zeptum-1.0.1.dist-info/RECORD
