Metadata-Version: 2.1
Name: zeptum
Version: 1.0.1
Summary: database package, simple and lightweight, without encryption, not recommended for use on servers with public access.
Author: harttman
